fabdem.py
fabdem-0.1.0.dist-info/LICENSE
fabdem-0.1.0.dist-info/WHEEL
fabdem-0.1.0.dist-info/METADATA
fabdem-0.1.0.dist-info/RECORD
