Metadata-Version: 2.1
Name: fabdem
Version: 0.1.0
Summary: Download FABDEM data: a DEM with forests and buildings removed using ML.
Author-email: Jan Tomec <jan.tomec@c3m.si>
Requires-Dist: requests >= 2.25
Requires-Dist: geopandas >= 0.14
Requires-Dist: tqdm >= 4.66
Requires-Dist: rasterio >= 1.3
Project-URL: Home, https://github.com/jantomec/fabdem
